nonebot_plugin_poker/__init__.py
nonebot_plugin_poker/utils.py
nonebot_plugin_poker-1.0.1.dist-info/METADATA
nonebot_plugin_poker-1.0.1.dist-info/WHEEL
nonebot_plugin_poker-1.0.1.dist-info/top_level.txt
nonebot_plugin_poker-1.0.1.dist-info/RECORD
