Metadata-Version: 2.4
Name: nonebot_plugin_poker
Version: 1.0.1
Summary: 详见https://github.com/MoonofBridge24/nonebot_plugin_poker
Author-email: MoonofBridge24 <moonofbridge24@foxmail.com>
Project-URL: Homepage, https://github.com/MoonofBridge24/nonebot_plugin_poker
Classifier: Programming Language :: Python :: 3
Classifier: License :: OSI Approved :: MIT License
Classifier: Operating System :: OS Independent
Requires-Python: <4.0,>=3.10
Requires-Dist: nonebot2>=2.3.0
Requires-Dist: nonebot-adapter-onebot>=2.3.0
